attio/__init__.py
attio/_version.py
attio/attributes.py
attio/basesdk.py
attio/call_recordings.py
attio/comments.py
attio/entries.py
attio/httpclient.py
attio/lists.py
attio/meetings.py
attio/meta.py
attio/notes.py
attio/objects.py
attio/py.typed
attio/records.py
attio/sdk.py
attio/sdkconfiguration.py
attio/tasks.py
attio/threads.py
attio/transcripts.py
attio/webhooks.py
attio/workspace_members.py
attio/_hooks/__init__.py
attio/_hooks/registration.py
attio/_hooks/sdkhooks.py
attio/_hooks/types.py
attio/errors/__init__.py
attio/errors/delete_v2_comments_comment_id_op.py
attio/errors/delete_v2_lists_list_entries_entry_id_op.py
attio/errors/delete_v2_notes_note_id_op.py
attio/errors/delete_v2_objects_object_records_record_id_op.py
attio/errors/delete_v2_tasks_task_id_op.py
attio/errors/delete_v2_webhooks_webhook_id_op.py
attio/errors/get_v2_comments_comment_id_op.py
attio/errors/get_v2_lists_list_entries_entry_id_attributes_attribute_valuesop.py
attio/errors/get_v2_lists_list_entries_entry_id_op.py
attio/errors/get_v2_lists_list_op.py
attio/errors/get_v2_meetings_meeting_id_call_recordings_call_recording_id_op.py
attio/errors/get_v2_meetings_meeting_id_op.py
attio/errors/get_v2_notes_note_id_op.py
attio/errors/get_v2_notesop.py
attio/errors/get_v2_objects_object_op.py
attio/errors/get_v2_objects_object_records_record_id_attributes_attribute_valuesop.py
attio/errors/get_v2_objects_object_records_record_id_op.py
attio/errors/get_v2_target_identifier_attributes_attribute_op.py
attio/errors/get_v2_target_identifier_attributes_attribute_optionsop.py
attio/errors/get_v2_target_identifier_attributes_attribute_statusesop.py
attio/errors/get_v2_tasks_task_id_op.py
attio/errors/get_v2_threads_thread_id_op.py
attio/errors/get_v2_webhooks_webhook_id_op.py
attio/errors/get_v2_workspace_members_workspace_member_id_op.py
attio/errors/no_response_error.py
attio/errors/patch_v2_lists_list_entries_entry_id_op.py
attio/errors/patch_v2_lists_list_op.py
attio-0.19.1.dist-info/METADATA
attio-0.19.1.dist-info/WHEEL
attio-0.19.1.dist-info/top_level.txt
attio-0.19.1.dist-info/RECORD
