Metadata-Version: 2.4
Name: attio
Version: 0.19.1
Summary: Attio API client library from elviskahoro
Author: elviskahoro
Requires-Python: >=3.9.2
Requires-Dist: httpcore>=1.0.9
Requires-Dist: httpx>=0.28.1
Requires-Dist: pydantic>=2.11.2
